ml_logger/__init__.py
ml_logger/logbook.py
ml_logger/metrics.py
ml_logger/types.py
ml_logger/utils.py
ml_logger/logger/__init__.py
ml_logger/logger/base.py
ml_logger/logger/filesystem.py
ml_logger/logger/mlflow.py
ml_logger/logger/mongo.py
ml_logger/logger/tensorboard.py
ml_logger/logger/wandb.py
ml_logger/parser/__init__.py
ml_logger/parser/base.py
ml_logger/parser/config.py
ml_logger/parser/log.py
ml_logger/parser/metric.py
ml_logger/parser/utils.py
ml_logger/parser/experiment/__init__.py
ml_logger/parser/experiment/experiment.py
ml_logger/parser/experiment/parser.py
mllogger-0.7.dist-info/LICENSE
mllogger-0.7.dist-info/METADATA
mllogger-0.7.dist-info/WHEEL
mllogger-0.7.dist-info/top_level.txt
mllogger-0.7.dist-info/RECORD
