Metadata-Version: 2.1
Name: mllogger
Version: 0.7
Summary: Logging Utility for ML Experiments
Home-page: https://github.com/shagunsodhani/ml-logger
Author: Shagun Sodhani
Author-email: sshagunsodhani@gmail.com
License: UNKNOWN
Platform: UNKNOWN
Classifier: Programming Language :: Python :: 3.6
Classifier: Programming Language :: Python :: 3.7
Classifier: Programming Language :: Python :: 3.8
Classifier: Programming Language :: Python :: 3.9
Classifier: License :: OSI Approved :: MIT License
Classifier: Operating System :: OS Independent
Requires-Python: >=3.6
Provides-Extra: all
Provides-Extra: dev
Requires-Dist: black (==19.10b0) ; extra == 'dev'
Requires-Dist: flake8-annotations (==2.4.1) ; extra == 'dev'
Requires-Dist: flake8-bandit (==2.1.2) ; extra == 'dev'
Requires-Dist: flake8-bugbear (==20.11.1) ; extra == 'dev'
Requires-Dist: flake8-comprehensions (==3.3.1) ; extra == 'dev'
Requires-Dist: flake8-docstrings (==1.5.0) ; extra == 'dev'
Requires-Dist: flake8 (==3.8.4) ; extra == 'dev'
Requires-Dist: isort (==5.6.4) ; extra == 'dev'
Requires-Dist: mypy (==0.790) ; extra == 'dev'
Requires-Dist: nox (==2020.8.22) ; extra == 'dev'
Requires-Dist: pre-commit (==2.9.3) ; extra == 'dev'
Requires-Dist: pytest (==6.2.1) ; extra == 'dev'
Requires-Dist: sphinx-autodoc-annotation (==1.0-1) ; extra == 'dev'
Requires-Dist: sphinx-rtd-theme (==0.5.0) ; extra == 'dev'
Requires-Dist: sphinx (==3.4.1) ; extra == 'dev'
Requires-Dist: sphinxcontrib-napoleon (==0.7) ; extra == 'dev'
Requires-Dist: towncrier (==19.2.0) ; extra == 'dev'
Requires-Dist: twine (==3.3.0) ; extra == 'dev'
Requires-Dist: typing-extensions (==3.7.4.3) ; extra == 'dev'
